loon/__init__.py
loon/classes.py
loon/skeleton.py
loon/tool.py
loon/utils.py
loon/data/PBS_CMDS.txt
loon/data/PBS_HEADER.txt
loon/data/mapping.csv
loon/data/pbs-template.pbs
loon/data/samplefile.csv
loon-0.4.2.dist-info/AUTHORS.rst
loon-0.4.2.dist-info/LICENSE.txt
loon-0.4.2.dist-info/METADATA
loon-0.4.2.dist-info/WHEEL
loon-0.4.2.dist-info/entry_points.txt
loon-0.4.2.dist-info/top_level.txt
loon-0.4.2.dist-info/RECORD
