Metadata-Version: 2.1
Name: loon
Version: 0.4.2
Summary: A Python toolkit for operating remote host based on SSH
Home-page: https://github.com/ShixiangWang/loon
Author: ShixiangWang
Author-email: w_shixiang@163.com
License: mit
Project-URL: Documentation, https://github.com/ShixiangWang/loon
Platform: any
Classifier: Development Status :: 4 - Beta
Classifier: Programming Language :: Python
Requires-Python: >=3.5
Requires-Dist: ssh2-python
Provides-Extra: testing
Requires-Dist: pytest ; extra == 'testing'
Requires-Dist: pytest-cov ; extra == 'testing'
